setup.cfg
setup.py
sy_probability/Binomialdistribution.py
sy_probability/Gaussiandistribution.py
sy_probability/Generaldistribution.py
sy_probability/__init__.py
sy_probability.egg-info/PKG-INFO
sy_probability.egg-info/SOURCES.txt
sy_probability.egg-info/dependency_links.txt
sy_probability.egg-info/not-zip-safe
sy_probability.egg-info/top_level.txt