Metadata-Version: 1.0
Name: sy-probability
Version: 1.0
Summary: Gaussian distributions and Binomial distribution
Home-page: UNKNOWN
Author: Amol Ambekar
Author-email: amolambekar10.aa@gmail.com
License: UNKNOWN
Platform: UNKNOWN
